freegenius/README.md
freegenius/__init__.py
freegenius/autoassist.py
freegenius/autobuilder.py
freegenius/autoretriever.py
freegenius/chatgpt.py
freegenius/codey.py
freegenius/commandprompt.py
freegenius/config.py
freegenius/eTextEdit.py
freegenius/geminipro.py
freegenius/geminiprovision.py
freegenius/groqchat.py
freegenius/llamacpp.py
freegenius/llamacppserver.py
freegenius/main.py
freegenius/ollamachat.py
freegenius/package_name.txt
freegenius/palm2.py
freegenius/qt.py
freegenius/rag.py
freegenius/requirements.txt
freegenius/servers.py
freegenius/systemtray.py
freegenius/audio/notification1.mp3
freegenius/audio/notification1_mild.mp3
freegenius/audio/notification2.mp3
freegenius/audio/notification2_mild.mp3
freegenius/docs/000_Home.md
freegenius/docs/Action Menu.md
freegenius/docs/Beyond LetMeDoItAI.md
freegenius/docs/CLI Options.md
freegenius/docs/Change AI Backends and Models.md
freegenius/docs/Configure Ollama Server.md
freegenius/docs/Customise Assistant Name.md
freegenius/docs/Download LLM in GGUF Format.md
freegenius/docs/Edit Config Manually.md
freegenius/docs/Examples.md
freegenius/docs/Fabric Integration.md
freegenius/docs/First launch.md
freegenius/docs/Function Call Approach with Any LLMs.md
freegenius/docs/GPU Acceleration with Llama_cpp server.md
freegenius/docs/GPU Acceleration.md
freegenius/docs/Google Cloud Service Credential Setup.md
freegenius/docs/Groq API Setup.md
freegenius/docs/Install FreeGenius.md
freegenius/docs/Install Python.md
freegenius/docs/Install ffmpeg.md
freegenius/docs/LetMeDoIt Mode.md
freegenius/docs/Miscellaneous.md
freegenius/docs/Offline TTS - Linux.md
freegenius/docs/Offline TTS - Windows.md
freegenius/docs/Offline TTS - macOS.md
freegenius/docs/OpenAI API Setup.md
freegenius/docs/Perplexica Integration.md
freegenius/docs/Plugins - Add Aliases.md
freegenius/docs/Plugins - Function Calling.md
freegenius/docs/Plugins - How to Write a Custom Plugin.md
freegenius/docs/Plugins - Input Suggestions.md
freegenius-0.3.16.dist-info/METADATA
freegenius-0.3.16.dist-info/WHEEL
freegenius-0.3.16.dist-info/entry_points.txt
freegenius-0.3.16.dist-info/top_level.txt
freegenius-0.3.16.dist-info/RECORD
