Metadata-Version: 2.1
Name: freegenius
Version: 0.3.16
Summary: FreeGenius AI, an advanced AI assistant that is capable of engaging in conversation and performing multi-step actions. Supports numerous open-source LLMs via Llama.cpp or Ollama or Groq Cloud API, with optional integration with AutoGen agents, OpenAI API, Google Gemini Pro, fabric and unlimited plugins.
Home-page: https://letmedoit.ai
Author: Eliran Wong
Author-email: support@letmedoit.ai
License: GNU General Public License (GPL)
Project-URL: Source, https://github.com/eliranwong/letmedoit
Project-URL: Tracker, https://github.com/eliranwong/letmedoit/issues
Project-URL: Documentation, https://github.com/eliranwong/letmedoit/wiki
Project-URL: Funding, https://www.paypal.me/letmedoitai
Keywords: ai assistant ollama llama llamacpp groq openai chatgpt gemini autogen rag agent stable-diffusion fabric
Platform: UNKNOWN
Classifier: Development Status :: 5 - Production/Stable
Classifier: Intended Audience :: End Users/Desktop
Classifier: Topic :: Utilities
Classifier: Topic :: Scientific/Engineering :: Artificial Intelligence
Classifier: Topic :: Software Development :: Build Tools
Classifier: License :: OSI Approved :: GNU General Public License v3 or later (GPLv3+)
Classifier: Programming Language :: Python :: 3.8
Classifier: Programming Language :: Python :: 3.9
Classifier: Programming Language :: Python :: 3.10
Classifier: Programming Language :: Python :: 3.11
Requires-Python: >=3.8, <3.12
Requires-Dist: PyMuPDF
Requires-Dist: PySide6
Requires-Dist: Pygments
Requires-Dist: SpeechRecognition
Requires-Dist: apsw
Requires-Dist: argparse
Requires-Dist: art
Requires-Dist: autogenstudio ==0.1.5
Requires-Dist: chromadb ==0.5.5
Requires-Dist: cmake ==3.29.3
Requires-Dist: colorama
Requires-Dist: datetime
Requires-Dist: docker
Requires-Dist: einops
Requires-Dist: elevenlabs ==1.8.0
Requires-Dist: feedparser
Requires-Dist: folium
Requires-Dist: gTTS
Requires-Dist: geocoder
Requires-Dist: geopy
Requires-Dist: google-cloud-aiplatform ==1.66.0
Requires-Dist: google-cloud-speech
Requires-Dist: google-cloud-texttospeech
Requires-Dist: googlesearch-python
Requires-Dist: groq ==0.11.0
Requires-Dist: guidance ==0.1.15
Requires-Dist: html2text
Requires-Dist: huggingface-hub ==0.24.7
Requires-Dist: langchain-community ==0.2.6
Requires-Dist: langchain-huggingface ==0.0.3
Requires-Dist: langchain-openai ==0.1.14
Requires-Dist: langchain ==0.2.6
Requires-Dist: llama-cpp-python[server] ==0.2.90
Requires-Dist: netifaces
Requires-Dist: numpy ==1.26.4
Requires-Dist: ollama ==0.3.3
Requires-Dist: openai-whisper
Requires-Dist: openai ==1.45.0
Requires-Dist: pendulum
Requires-Dist: pillow
Requires-Dist: prompt-toolkit
Requires-Dist: protobuf ==4.25.3
Requires-Dist: psutil
Requires-Dist: pyautogen[autobuild,retrievechat] ==0.3.0
Requires-Dist: pydub
Requires-Dist: pygame
Requires-Dist: pypdf
Requires-Dist: pyperclip
Requires-Dist: pytz
Requires-Dist: pywhatkit
Requires-Dist: qrcode
Requires-Dist: rembg
Requires-Dist: requests
Requires-Dist: seaborn[stats]
Requires-Dist: sentence-transformers ==3.0.1
Requires-Dist: setuptools-rust
Requires-Dist: sounddevice ==0.4.7
Requires-Dist: soundfile ==0.12.1
Requires-Dist: stable-diffusion-cpp-python
Requires-Dist: sympy
Requires-Dist: tiktoken ==0.7.0
Requires-Dist: toolmate
Requires-Dist: torch ==2.3.0
Requires-Dist: torchaudio ==2.3.0
Requires-Dist: torchvision ==0.18.0
Requires-Dist: transformers ==4.42.3
Requires-Dist: unstructured[all-docs]
Requires-Dist: yfinance
Requires-Dist: yt-dlp
